datamodel_converter/__init__.py
datamodel_converter/py.typed
datamodel_converter/pydantic_converter.py
datamodel_converter-0.0.2.dist-info/METADATA
datamodel_converter-0.0.2.dist-info/WHEEL
datamodel_converter-0.0.2.dist-info/licenses/LICENSE
datamodel_converter-0.0.2.dist-info/RECORD
