Metadata-Version: 2.4
Name: datamodel-converter
Version: 0.0.2
Summary: Convert Pydantic models to OpenAI output schema, OpenAI tool schema, and more.
License: MIT License
License-File: LICENSE
Requires-Python: >=3.12
Requires-Dist: pydantic>=2.11.2
